{"scene_id":"botswana","recipe":"V9","scheme":"uniform","Q":32,"B":145,"D":2775,"V_full":1696,"V_actual":708,"doc_length_distribution":{"mean":1.0,"std":0.0,"min":1,"p25":1.0,"p50":1.0,"p75":1.0,"max":1},"zero_token_doc_rate":0.0,"corpus_marginal_entropy_bits":8.1561,"top_tokens_by_count":[{"token":"region356_q07","count":83,"p_global":0.02991},{"token":"region023_q07","count":67,"p_global":0.024144},{"token":"region023_q09","count":65,"p_global":0.023423},{"token":"region356_q06","count":64,"p_global":0.023063},{"token":"region023_q10","count":64,"p_global":0.023063},{"token":"region356_q08","count":60,"p_global":0.021622},{"token":"region023_q12","count":53,"p_global":0.019099},{"token":"region356_q09","count":51,"p_global":0.018378},{"token":"region023_q11","count":51,"p_global":0.018378},{"token":"region023_q06","count":51,"p_global":0.018378},{"token":"region023_q13","count":49,"p_global":0.017658},{"token":"region023_q08","count":47,"p_global":0.016937},{"token":"region023_q15","count":41,"p_global":0.014775},{"token":"region356_q05","count":41,"p_global":0.014775},{"token":"region356_q10","count":38,"p_global":0.013694},{"token":"region356_q04","count":35,"p_global":0.012613},{"token":"region023_q14","count":34,"p_global":0.012252},{"token":"region023_q05","count":33,"p_global":0.011892},{"token":"region356_q03","count":32,"p_global":0.011532},{"token":"region356_q02","count":31,"p_global":0.011171}],"wavelengths_nm_first_last":[400.0,2500.0],"local_doc_term_path":"data/local/wordifications/V9/uniform_Q32/botswana/doc_term.npz","generated_at":"2026-05-04T03:00:33Z","builder_version":"build_wordifications_v6plus v0.1"}