{"scene_id":"indian-pines-corrected","recipe":"V2","scheme":"quantile","Q":32,"B":200,"D":2812,"V_full":32,"V_actual":32,"doc_length_distribution":{"mean":200.0,"std":0.0,"min":200,"p25":200.0,"p50":200.0,"p75":200.0,"max":200},"zero_token_doc_rate":0.0,"corpus_marginal_entropy_bits":4.9965,"top_tokens_by_count":[{"token":"q00","count":20015,"p_global":0.035589},{"token":"q04","count":19806,"p_global":0.035217},{"token":"q13","count":19729,"p_global":0.03508},{"token":"q18","count":19701,"p_global":0.03503},{"token":"q22","count":19684,"p_global":0.035},{"token":"q27","count":19668,"p_global":0.034972},{"token":"q31","count":19636,"p_global":0.034915},{"token":"q09","count":19482,"p_global":0.034641},{"token":"q07","count":17242,"p_global":0.030658},{"token":"q01","count":17193,"p_global":0.030571},{"token":"q08","count":17050,"p_global":0.030317},{"token":"q14","count":17014,"p_global":0.030252},{"token":"q11","count":16912,"p_global":0.030071},{"token":"q25","count":16904,"p_global":0.030057},{"token":"q30","count":16894,"p_global":0.030039},{"token":"q26","count":16883,"p_global":0.03002},{"token":"q19","count":16881,"p_global":0.030016},{"token":"q23","count":16880,"p_global":0.030014},{"token":"q12","count":16876,"p_global":0.030007},{"token":"q28","count":16872,"p_global":0.03}],"wavelengths_nm_first_last":[400.0,2500.0],"local_doc_term_path":"data/local/wordifications/V2/quantile_Q32/indian-pines-corrected/doc_term.npz","generated_at":"2026-05-03T04:21:30Z","builder_version":"build_wordifications v0.1"}