{"scene_id":"indian-pines-corrected","recipe":"V1","scheme":"uniform","Q":16,"B":200,"D":2812,"V_full":200,"V_actual":169,"doc_length_distribution":{"mean":977.957,"std":163.1449,"min":607,"p25":848.0,"p50":1024.0,"p75":1125.0,"max":1223},"zero_token_doc_rate":0.0,"corpus_marginal_entropy_bits":6.8644,"top_tokens_by_count":[{"token":"b041","count":41829,"p_global":0.01521},{"token":"b040","count":41732,"p_global":0.015175},{"token":"b042","count":41387,"p_global":0.01505},{"token":"b037","count":41063,"p_global":0.014932},{"token":"b038","count":40934,"p_global":0.014885},{"token":"b043","count":40439,"p_global":0.014705},{"token":"b047","count":39252,"p_global":0.014273},{"token":"b049","count":39005,"p_global":0.014184},{"token":"b048","count":38938,"p_global":0.014159},{"token":"b051","count":38710,"p_global":0.014076},{"token":"b050","count":38349,"p_global":0.013945},{"token":"b052","count":37474,"p_global":0.013627},{"token":"b044","count":36499,"p_global":0.013272},{"token":"b036","count":36349,"p_global":0.013218},{"token":"b046","count":35948,"p_global":0.013072},{"token":"b006","count":34138,"p_global":0.012414},{"token":"b005","count":33597,"p_global":0.012217},{"token":"b045","count":33240,"p_global":0.012087},{"token":"b007","count":33129,"p_global":0.012047},{"token":"b008","count":32827,"p_global":0.011937}],"wavelengths_nm_first_last":[400.0,2500.0],"local_doc_term_path":"data/local/wordifications/V1/uniform_Q16/indian-pines-corrected/doc_term.npz","generated_at":"2026-05-03T04:21:30Z","builder_version":"build_wordifications v0.1"}