{"scene_id":"salinas-corrected","recipe":"V4","scheme":"lloyd_max","Q":16,"B":204,"D":3520,"V_full":204,"V_actual":200,"doc_length_distribution":{"mean":1358.546,"std":192.1103,"min":905,"p25":1240.0,"p50":1437.5,"p75":1503.25,"max":1613},"zero_token_doc_rate":0.0,"corpus_marginal_entropy_bits":7.5545,"top_tokens_by_count":[{"token":"d1_b043","count":52771,"p_global":0.011035},{"token":"d1_b063","count":46801,"p_global":0.009787},{"token":"d1_b039","count":46574,"p_global":0.009739},{"token":"d1_b003","count":44138,"p_global":0.00923},{"token":"d1_b064","count":43816,"p_global":0.009163},{"token":"d1_b083","count":43238,"p_global":0.009042},{"token":"d1_b002","count":42671,"p_global":0.008923},{"token":"d1_b040","count":42217,"p_global":0.008828},{"token":"d1_b084","count":41473,"p_global":0.008673},{"token":"d1_b036","count":38641,"p_global":0.00808},{"token":"d1_b065","count":38598,"p_global":0.008071},{"token":"d1_b062","count":38461,"p_global":0.008043},{"token":"d1_b049","count":37119,"p_global":0.007762},{"token":"d1_b004","count":36425,"p_global":0.007617},{"token":"d1_b007","count":36368,"p_global":0.007605},{"token":"d1_b001","count":35039,"p_global":0.007327},{"token":"d1_b035","count":34895,"p_global":0.007297},{"token":"d1_b050","count":34278,"p_global":0.007168},{"token":"d1_b115","count":33911,"p_global":0.007091},{"token":"d1_b114","count":33817,"p_global":0.007072}],"wavelengths_nm_first_last":[400.0,2500.0],"local_doc_term_path":"data/local/wordifications/V4/lloyd_max_Q16/salinas-corrected/doc_term.npz","generated_at":"2026-05-04T00:09:15Z","builder_version":"build_wordifications_v4plus v0.1"}