{"subset_code":"GEOCHEM","topic_count":5,"document_count":106,"covariates_in_dmr":["coarse","coarse","fine","fine","coarse","coarse","fine","fine","coarse","coarse","fine","fine","coarse","coarse","fine","fine","coarse","coarse","fine","fine","coarse","coarse","fine","fine","coarse","coarse","fine","fine","coarse","coarse","fine","fine","coarse","coarse","fine","fine","coarse","coarse","fine","fine","coarse","coarse","fine","fine","coarse","coarse","fine","fine","coarse","coarse","fine","fine","coarse","coarse","fine","fine","coarse","coarse","fine","fine","coarse","coarse","fine","fine","coarse","coarse","fine","fine","coarse","coarse","fine","fine","coarse","coarse","fine","fine","coarse","coarse","fine","fine","coarse","coarse","fine","fine","coarse","coarse","fine","fine","fine","fine","coarse","coarse","fine","fine","coarse","coarse","fine","fine","coarse","coarse","fine","fine","fine","fine","fine","fine"],"target_mi_against_theta":{"Al":{"per_feature_mi_sum_nats":0.256389,"per_feature_mi_max":0.125673,"per_feature_mi":[0.0,0.037655,0.0,0.125673,0.093061],"n_observed":106},"As":{"per_feature_mi_sum_nats":0.121392,"per_feature_mi_max":0.103369,"per_feature_mi":[0.0,0.016746,0.001277,0.103369,0.0],"n_observed":106},"Ca":{"per_feature_mi_sum_nats":0.163403,"per_feature_mi_max":0.089263,"per_feature_mi":[0.089263,0.049737,0.0,0.01814,0.006263],"n_observed":106},"Cu":{"per_feature_mi_sum_nats":0.244562,"per_feature_mi_max":0.143989,"per_feature_mi":[0.143989,0.0,0.0,0.029594,0.070978],"n_observed":106},"Fe":{"per_feature_mi_sum_nats":0.139606,"per_feature_mi_max":0.107004,"per_feature_mi":[0.0,0.032602,0.0,0.107004,0.0],"n_observed":106},"K":{"per_feature_mi_sum_nats":0.159373,"per_feature_mi_max":0.112748,"per_feature_mi":[0.005017,0.041608,0.0,0.112748,0.0],"n_observed":106},"Mo":{"per_feature_mi_sum_nats":0.20913,"per_feature_mi_max":0.104632,"per_feature_mi":[0.0,0.104632,0.007682,0.091976,0.004841],"n_observed":106},"Nb":{"per_feature_mi_sum_nats":0.044279,"per_feature_mi_max":0.044279,"per_feature_mi":[0.0,0.0,0.0,0.044279,0.0],"n_observed":106},"P":{"per_feature_mi_sum_nats":0.07679,"per_feature_mi_max":0.07679,"per_feature_mi":[0.0,0.0,0.0,0.07679,0.0],"n_observed":106},"Pb":{"per_feature_mi_sum_nats":0.162971,"per_feature_mi_max":0.084782,"per_feature_mi":[0.013863,0.0,0.0,0.084782,0.064326],"n_observed":106},"Rb":{"per_feature_mi_sum_nats":0.083941,"per_feature_mi_max":0.036799,"per_feature_mi":[0.0,0.0,0.019546,0.036799,0.027595],"n_observed":106},"S":{"per_feature_mi_sum_nats":0.318846,"per_feature_mi_max":0.130965,"per_feature_mi":[0.042187,0.027044,0.000897,0.130965,0.117754],"n_observed":106},"Si":{"per_feature_mi_sum_nats":0.189862,"per_feature_mi_max":0.081082,"per_feature_mi":[0.021016,0.0,0.081082,0.070629,0.017134],"n_observed":106},"Sr":{"per_feature_mi_sum_nats":0.080832,"per_feature_mi_max":0.051485,"per_feature_mi":[0.051485,0.0,0.0,0.029347,0.0],"n_observed":106},"Ti":{"per_feature_mi_sum_nats":0.09079,"per_feature_mi_max":0.051209,"per_feature_mi":[0.0,0.0,0.039581,0.051209,0.0],"n_observed":106},"Y":{"per_feature_mi_sum_nats":0.141155,"per_feature_mi_max":0.048588,"per_feature_mi":[0.02767,0.048588,0.0,0.041068,0.023829],"n_observed":106},"Zn":{"per_feature_mi_sum_nats":0.036725,"per_feature_mi_max":0.036725,"per_feature_mi":[0.0,0.0,0.036725,0.0,0.0],"n_observed":106},"Zr":{"per_feature_mi_sum_nats":0.079164,"per_feature_mi_max":0.031947,"per_feature_mi":[0.025157,0.0,0.02206,0.031947,0.0],"n_observed":106}},"ranking_by_max_mi":[{"target":"Cu","max_topic_mi":0.143989,"n_observed":106},{"target":"S","max_topic_mi":0.130965,"n_observed":106},{"target":"Al","max_topic_mi":0.125673,"n_observed":106},{"target":"K","max_topic_mi":0.112748,"n_observed":106},{"target":"Fe","max_topic_mi":0.107004,"n_observed":106},{"target":"Mo","max_topic_mi":0.104632,"n_observed":106},{"target":"As","max_topic_mi":0.103369,"n_observed":106},{"target":"Ca","max_topic_mi":0.089263,"n_observed":106},{"target":"Pb","max_topic_mi":0.084782,"n_observed":106},{"target":"Si","max_topic_mi":0.081082,"n_observed":106}],"framework_axis":"B-4 (master plan Addendum B Axis D): MI(theta; HIDSAG measurement)","generated_at":"2026-05-06T07:03:23Z","builder_version":"build_mutual_information v0.1"}